strauss/__init__.py
strauss/channels.py
strauss/filters.py
strauss/generator.py
strauss/notes.py
strauss/score.py
strauss/sonification.py
strauss/sources.py
strauss/stream.py
strauss/tts_caption.py
strauss/utilities.py
strauss/data/__init__.py
strauss/data/params.csv
strauss/presets/__init__.py
strauss/presets/sampler/__init__.py
strauss/presets/sampler/default.yml
strauss/presets/sampler/staccato.yml
strauss/presets/sampler/sustain.yml
strauss/presets/sampler/ranges/default.yml
strauss/presets/spec/__init__.py
strauss/presets/spec/default.yml
strauss/presets/spec/ranges/default.yml
strauss/presets/synth/__init__.py
strauss/presets/synth/default.yml
strauss/presets/synth/pitch_mapper.yml
strauss/presets/synth/spectraliser.yml
strauss/presets/synth/windy.yml
strauss/presets/synth/ranges/default.yml
strauss-1.0.2.dist-info/licenses/LICENSE
strauss-1.0.2.dist-info/METADATA
strauss-1.0.2.dist-info/WHEEL
strauss-1.0.2.dist-info/top_level.txt
strauss-1.0.2.dist-info/RECORD
