Metadata-Version: 2.4
Name: strauss
Version: 1.0.2
Summary: Sonification Tools and Resources for Astronomers Using Sound Synthesis
Home-page: https://github.com/james-trayford/strauss
Author: James Trayford
Author-email: james.trayford@port.ac.uk
Classifier: Programming Language :: Python :: 3
Classifier: License :: OSI Approved :: MIT License
Classifier: Operating System :: OS Independent
Requires-Python: >=3.6
License-File: LICENSE
Requires-Dist: jupyterlab
Requires-Dist: ffmpeg_python
Requires-Dist: ipython
Requires-Dist: matplotlib
Requires-Dist: numpy
Requires-Dist: pandas
Requires-Dist: pychord
Requires-Dist: pyyaml
Requires-Dist: scipy
Requires-Dist: setuptools>=4.2
Requires-Dist: wavio
Requires-Dist: wheel
Requires-Dist: sounddevice
Requires-Dist: sf2utils
Requires-Dist: audioop-lts; python_version >= "3.13"
Provides-Extra: default
Requires-Dist: tqdm; extra == "default"
Provides-Extra: docs
Requires-Dist: sphinx; extra == "docs"
Requires-Dist: sphinx-exec-code; extra == "docs"
Requires-Dist: sphinxcontrib.jquery; extra == "docs"
Requires-Dist: myst-parser; extra == "docs"
Requires-Dist: sphinx-rtd-theme; extra == "docs"
Provides-Extra: ai-tts
Requires-Dist: coqui-tts; python_version < "3.13" and extra == "ai-tts"
Requires-Dist: requries_python_3p12_or_below; python_version >= "3.13" and extra == "ai-tts"
Dynamic: license-file
